mrtopo/__init__.py
mrtopo/__main__.py
mrtopo/cli.py
mrtopo/analyzer/__init__.py
mrtopo/analyzer/analyzer.py
mrtopo/error/__init__.py
mrtopo/error/error.py
mrtopo/interpreter/__init__.py
mrtopo/interpreter/interpreter.py
mrtopo/logger/__init__.py
mrtopo/logger/log.py
mrtopo/mutator/__init__.py
mrtopo/mutator/mutator.py
mrtopo/mutator/operators.py
mrtopo/structures/__init__.py
mrtopo/structures/config.py
mrtopo/structures/mutantnetwork.py
mrtopo/structures/network.py
mrtopo/structures/topology.py
mrtopo/structures/networks/__init__.py
mrtopo/structures/networks/ring/__init__.py
mrtopo/structures/networks/ring/ring.py
mrtopo/tester/__init__.py
mrtopo/tester/tester.py
mrtopo/translator/__init__.py
mrtopo/translator/mrtopoio.py
mrtopo/translator/translator.py
mrtopo/util/__init__.py
mrtopo/util/filetype.py
mrtopo/util/iofunctor.py
mrtopo/validator/__init__.py
mrtopo/validator/validator.py
mrtopo-0.1.7.dist-info/LICENSE
mrtopo-0.1.7.dist-info/METADATA
mrtopo-0.1.7.dist-info/WHEEL
mrtopo-0.1.7.dist-info/entry_points.txt
mrtopo-0.1.7.dist-info/top_level.txt
mrtopo-0.1.7.dist-info/RECORD
