Metadata-Version: 2.1
Name: mrtopo
Version: 0.1.7
Summary: Mutate Mininet topology files with MrTopo
Home-page: https://github.com/FaizChishtie/mrtopo
Author: faizchishtie
Author-email: faizchishtie@gmail.com
License: MIT
Keywords: topology network startup
Platform: UNKNOWN
Classifier: Development Status :: 3 - Alpha
Classifier: Environment :: Console
Classifier: Intended Audience :: Developers
Classifier: License :: OSI Approved :: MIT License
Classifier: Operating System :: OS Independent
Classifier: Programming Language :: Python :: 3
Classifier: Programming Language :: Python :: 3.6
Classifier: Programming Language :: Python :: 3.7
Classifier: Programming Language :: Python :: 3.8
Classifier: Programming Language :: Python :: 3.9
Classifier: Topic :: Utilities
Classifier: Typing :: Typed
Requires-Python: >=3.0
Requires-Dist: mininet
Requires-Dist: click
